CMakeLists.txt
LICENSE
MANIFEST.in
README.md
pyproject.toml
setup.py
./phot/__init__.py
./phot/components/__init__.py
./phot/components/adaptive_equalizer.py
./phot/components/analyzer.py
./phot/components/ber.py
./phot/components/bps.py
./phot/components/dac_noise.py
./phot/components/eye_diagram.py
./phot/components/fiber.py
./phot/components/frame_syncer.py
./phot/components/gaussian_noise.py
./phot/components/modem.py
./phot/components/phase_noise.py
./phot/components/pulse_shaping.py
./phot/components/receiver.py
./phot/components/rx_simple.py
./phot/components/transmitter.py
./phot/optical/__init__.py
./phot/optical/awgn.py
./phot/optical/bit_error.py
./phot/optical/bps.py
./phot/optical/cdc.py
./phot/optical/cma_rde.py
./phot/optical/dbp_compensate.py
./phot/optical/fiber_cupy.py
./phot/optical/fiber_numpy.py
./phot/optical/fiber_torch.py
./phot/optical/fine_sync.py
./phot/optical/linewidth_noise.py
./phot/optical/offset_compens.py
./phot/optical/orthog.py
./phot/optical/resolution.py
./phot/optical/signal_power.py
./phot/utils/__init__.py
./phot/utils/dsp.py
./phot/utils/gpu.py
./phot/utils/io.py
./phot/utils/logging.py
./phot/utils/mathutils.py
./phot/utils/plot.py
./phot/utils/settings.py
phot/__init__.py
phot/components/__init__.py
phot/components/adaptive_equalizer.py
phot/components/analyzer.py
phot/components/ber.py
phot/components/bps.py
phot/components/dac_noise.py
phot/components/eye_diagram.py
phot/components/fiber.py
phot/components/frame_syncer.py
phot/components/gaussian_noise.py
phot/components/modem.py
phot/components/phase_noise.py
phot/components/pulse_shaping.py
phot/components/receiver.py
phot/components/rx_simple.py
phot/components/transmitter.py
phot/csrc/main.cpp
phot/optical/__init__.py
phot/optical/awgn.py
phot/optical/bit_error.py
phot/optical/bps.py
phot/optical/cdc.py
phot/optical/cma_rde.py
phot/optical/dbp_compensate.py
phot/optical/fiber_cupy.py
phot/optical/fiber_numpy.py
phot/optical/fiber_torch.py
phot/optical/fine_sync.py
phot_py_tyz.egg-info/PKG-INFO
phot_py_tyz.egg-info/SOURCES.txt
phot_py_tyz.egg-info/dependency_links.txt
phot_py_tyz.egg-info/requires.txt
phot_py_tyz.egg-info/top_level.txt