Metadata-Version: 2.1
Name: phot-py-tyz
Version: 0.2.12
Summary: A Python library for the simulation of optical fiber transmission
Home-page: https://github.com/phot-lab/pyphot
Author: Yunzhou Tang
Author-email: 1209665265@qq.com
Requires-Python: >=3.7
License-File: LICENSE
